httpds_python/__init__.py
httpds_python/server.py
httpds_python-1.0.1.dist-info/METADATA
httpds_python-1.0.1.dist-info/WHEEL
httpds_python-1.0.1.dist-info/entry_points.txt
httpds_python-1.0.1.dist-info/top_level.txt
httpds_python-1.0.1.dist-info/RECORD
