Metadata-Version: 2.1
Name: httpds-python
Version: 1.0.1
Summary: Simple HTTPS server with CORS support
Home-page: https://github.com/rayven2129/httpds-python
Author: Rayven Dela Cruz
Author-email: vergaradelacruz.rayven@gmail.com
Classifier: Programming Language :: Python :: 3
Classifier: License :: OSI Approved :: MIT License
Classifier: Operating System :: OS Independent
Requires-Python: >=3.6
